databricks_filesystem/__init__.py
databricks_filesystem/src/__init__.py
databricks_filesystem/src/filesystem.py
databricks_filesystem-0.0.4.dist-info/LICENSE
databricks_filesystem-0.0.4.dist-info/METADATA
databricks_filesystem-0.0.4.dist-info/WHEEL
databricks_filesystem-0.0.4.dist-info/top_level.txt
databricks_filesystem-0.0.4.dist-info/RECORD
