Metadata-Version: 2.1
Name: databricks_filesystem
Version: 0.0.4
Summary: Databricks Utils does not support few crucial file system operations like recursive directory listing, pattern-matching for files, listing only directories or files, and more. This package provides seamless execution of these tasks.
Home-page: https://medium.com/data-engineer-things/finally-in-databricks-we-can-now-perform-recursive-directory-listing-and-many-more-operations-c5f32aad78e7
Author: Rahul Madhani
Author-email: madhani.rahul@gmail.com
Project-URL: Documentation, https://medium.com/data-engineer-things/finally-in-databricks-we-can-now-perform-recursive-directory-listing-and-many-more-operations-c5f32aad78e7
Project-URL: Source, https://github.com/madhanir/databricks_filesystem
Classifier: Development Status :: 5 - Production/Stable
Classifier: Intended Audience :: Developers
Classifier: License :: OSI Approved :: MIT License
Classifier: Natural Language :: English
Classifier: Operating System :: OS Independent
Classifier: Programming Language :: Cython
Classifier: Programming Language :: Python
Classifier: Topic :: Scientific/Engineering
Classifier: Topic :: Software Development :: Libraries
Classifier: Topic :: Software Development :: Libraries :: Python Modules
License-File: LICENSE
